README.md
setup.py
wf_autodialer_entities/__init__.py
wf_autodialer_entities/agent.py
wf_autodialer_entities/base.py
wf_autodialer_entities/call.py
wf_autodialer_entities/conference.py
wf_autodialer_entities/opportunity.py
wf_autodialer_entities/queue.py
wf_autodialer_entities/tenant.py
wf_autodialer_entities/user.py
wf_autodialer_entities.egg-info/PKG-INFO
wf_autodialer_entities.egg-info/SOURCES.txt
wf_autodialer_entities.egg-info/dependency_links.txt
wf_autodialer_entities.egg-info/top_level.txt