Metadata-Version: 2.1
Name: wf-autodialer-entities
Version: 0.1.2
Summary: Webforce autodialer entities
Home-page: UNKNOWN
Author: Webforce
Author-email: master@webforcehq.com
License: UNKNOWN
Platform: UNKNOWN
Classifier: Programming Language :: Python :: 3
Classifier: License :: OSI Approved :: MIT License
Classifier: Operating System :: OS Independent
Requires-Python: >=3.6
